tidalapi/__init__.py
tidalapi/album.py
tidalapi/artist.py
tidalapi/exceptions.py
tidalapi/genre.py
tidalapi/media.py
tidalapi/mix.py
tidalapi/page.py
tidalapi/playlist.py
tidalapi/py.typed
tidalapi/request.py
tidalapi/session.py
tidalapi/types.py
tidalapi/user.py
tidalapi/workers.py
tidalapi-0.8.10.dist-info/METADATA
tidalapi-0.8.10.dist-info/WHEEL
tidalapi-0.8.10.dist-info/licenses/LICENSE
tidalapi-0.8.10.dist-info/RECORD
