Metadata-Version: 2.4
Name: tidalapi
Version: 0.8.10
Summary: Unofficial API for TIDAL music streaming service.
License: LGPL-3.0-or-later
License-File: LICENSE
Author: Thomas Amland
Author-email: thomas.amland@googlemail.com
Maintainer: tehkillerbee
Maintainer-email: tehkillerbee@users.noreply.github.com
Requires-Python: >=3.8,<4.0
Classifier: Development Status :: 4 - Beta
Classifier: Intended Audience :: Developers
Classifier: License :: OSI Approved :: GNU Lesser General Public License v3 (LGPLv3)
Classifier: License :: OSI Approved :: GNU Lesser General Public License v3 or later (LGPLv3+)
Classifier: Programming Language :: Python :: 3
Classifier: Programming Language :: Python :: 3.8
Classifier: Programming Language :: Python :: 3.9
Classifier: Programming Language :: Python :: 3.10
Classifier: Programming Language :: Python :: 3.11
Classifier: Programming Language :: Python :: 3.12
Classifier: Programming Language :: Python :: 3.13
Classifier: Programming Language :: Python :: 3.14
Classifier: Typing :: Typed
Requires-Dist: isodate (>=0.7.2,<0.8.0)
Requires-Dist: mpegdash (>=0.4.0,<0.5.0)
Requires-Dist: pyaes (>=1.6.1,<2.0.0)
Requires-Dist: python-dateutil (>=2.8.2,<3.0.0)
Requires-Dist: ratelimit (>=2.2.1,<3.0.0)
Requires-Dist: requests (>=2.32.3,<3.0.0)
Requires-Dist: typing-extensions (>=4.12.2,<5.0.0)
Project-URL: Documentation, https://tidalapi.netlify.app
Project-URL: Homepage, https://tidalapi.netlify.app
Project-URL: Repository, https://github.com/EbbLabs/python-tidal
